pysupladevice/__init__.py
pysupladevice/channels.py
pysupladevice/device.py
pysupladevice/network.py
pysupladevice/proto.py
pysupladevice-0.1.7.dist-info/LICENSE
pysupladevice-0.1.7.dist-info/METADATA
pysupladevice-0.1.7.dist-info/WHEEL
pysupladevice-0.1.7.dist-info/top_level.txt
pysupladevice-0.1.7.dist-info/RECORD
