Metadata-Version: 2.1
Name: pysupladevice
Version: 0.1.7
Requires-Python: >=3.7
License-File: LICENSE
Provides-Extra: dev
Requires-Dist: build ; extra == 'dev'
Requires-Dist: mypy ; extra == 'dev'
Requires-Dist: pre-commit ; extra == 'dev'
Requires-Dist: pylint ; extra == 'dev'
Requires-Dist: pylint-pytest ; extra == 'dev'
Requires-Dist: pytest ; extra == 'dev'
Requires-Dist: pytest-cov ; extra == 'dev'
Requires-Dist: pytest-mock ; extra == 'dev'
Requires-Dist: pytest-xdist ; extra == 'dev'
